<?xml version="1.0" encoding="UTF-8"?>
<wsp:Policy xmlns:L7p="http://www.layer7tech.com/ws/policy" xmlns:wsp="http://schemas.xmlsoap.org/ws/2002/12/policy">
    <wsp:All wsp:Usage="Required">
        <L7p:CommentAssertion>
            <L7p:Comment stringValue="Target Configuration Policy: &quot;MAG OTP Configuration&quot;"/>
        </L7p:CommentAssertion>
        <L7p:CommentAssertion>
            <L7p:Comment stringValue="=== Set custom values for Context Variables below ==="/>
        </L7p:CommentAssertion>
        <L7p:CommentAssertion>
            <L7p:Comment stringValue="=== Add any new Context Variables or extensions below ==="/>
        </L7p:CommentAssertion>
        <L7p:SetVariable>
            <L7p:AssertionComment assertionComment="included">
                <L7p:Properties mapValue="included">
                    <L7p:entry>
                        <L7p:key stringValue="LEFT.COMMENT"/>
                        <L7p:value stringValue="Default OTP type"/>
                    </L7p:entry>
                    <L7p:entry>
                        <L7p:key stringValue="RIGHT.COMMENT"/>
                        <L7p:value stringValue="Possible values are alphanumeric or numerical"/>
                    </L7p:entry>
                </L7p:Properties>
            </L7p:AssertionComment>
            <L7p:Base64Expression stringValue="bnVtZXJpY2Fs"/>
            <L7p:VariableToSet stringValue="defaultOtpType"/>
        </L7p:SetVariable>
        <L7p:SetVariable>
            <L7p:AssertionComment assertionComment="included">
                <L7p:Properties mapValue="included">
                    <L7p:entry>
                        <L7p:key stringValue="LEFT.COMMENT"/>
                        <L7p:value stringValue="Default OTP length to be generated"/>
                    </L7p:entry>
                    <L7p:entry>
                        <L7p:key stringValue="RIGHT.COMMENT"/>
                        <L7p:value stringValue="1 to 64"/>
                    </L7p:entry>
                </L7p:Properties>
            </L7p:AssertionComment>
            <L7p:Base64Expression stringValue="Ng=="/>
            <L7p:VariableToSet stringValue="defaultOtpLength"/>
        </L7p:SetVariable>
    </wsp:All>
</wsp:Policy>