<?xml version="1.0" encoding="UTF-8"?>
<wsp:Policy xmlns:L7p="http://www.layer7tech.com/ws/policy" xmlns:wsp="http://schemas.xmlsoap.org/ws/2002/12/policy">
    <wsp:All wsp:Usage="Required">
        <L7p:CommentAssertion>
            <L7p:Comment stringValue=" ============================================"/>
        </L7p:CommentAssertion>
        <L7p:CommentAssertion>
            <L7p:Comment stringValue=" === ***  THIS POLICY IS READ ONLY ***"/>
        </L7p:CommentAssertion>
        <L7p:CommentAssertion>
            <L7p:Comment stringValue=" === If you have the need to customize this policy"/>
        </L7p:CommentAssertion>
        <L7p:CommentAssertion>
            <L7p:Comment stringValue=" === please contact CA APIM Support so we can improve customization capability"/>
        </L7p:CommentAssertion>
        <L7p:CommentAssertion>
            <L7p:Comment stringValue=" ============================================"/>
        </L7p:CommentAssertion>
        <L7p:CommentAssertion>
            <L7p:Comment stringValue="This policy can be found and should be used as 'Encapsulated Assertion'!"/>
        </L7p:CommentAssertion>
        <L7p:SetVariable>
            <L7p:Base64Expression stringValue=""/>
            <L7p:VariableToSet stringValue="error.code"/>
        </L7p:SetVariable>
        <L7p:SetVariable>
            <L7p:Base64Expression stringValue=""/>
            <L7p:VariableToSet stringValue="content-type"/>
        </L7p:SetVariable>
        <L7p:SetVariable>
            <L7p:Base64Expression stringValue=""/>
            <L7p:VariableToSet stringValue="result"/>
        </L7p:SetVariable>
        <wsp:OneOrMore wsp:Usage="Required">
            <L7p:ComparisonAssertion>
                <L7p:CaseSensitive booleanValue="false"/>
                <L7p:Expression1 stringValue="${magidentifier}"/>
                <L7p:Expression2 stringValue="activated"/>
                <L7p:MultivaluedComparison multivaluedComparison="FAIL"/>
                <L7p:Negate booleanValue="true"/>
                <L7p:Operator operator="EMPTY"/>
                <L7p:Predicates predicates="included">
                    <L7p:item binary="included">
                        <L7p:CaseSensitive booleanValue="false"/>
                        <L7p:Negated booleanValue="true"/>
                        <L7p:Operator operator="EMPTY"/>
                        <L7p:RightValue stringValue="activated"/>
                    </L7p:item>
                </L7p:Predicates>
            </L7p:ComparisonAssertion>
            <wsp:All wsp:Usage="Required">
                <L7p:AuditDetailAssertion>
                    <L7p:Detail stringValue="No magidentifier was given"/>
                </L7p:AuditDetailAssertion>
                <L7p:SetVariable>
                    <L7p:Base64Expression stringValue="MTAz"/>
                    <L7p:VariableToSet stringValue="error.code"/>
                </L7p:SetVariable>
                <L7p:FalseAssertion/>
                <L7p:assertionComment>
                    <L7p:Properties mapValue="included">
                        <L7p:entry>
                            <L7p:key stringValue="LEFT.COMMENT"/>
                            <L7p:value stringValue="Error"/>
                        </L7p:entry>
                    </L7p:Properties>
                </L7p:assertionComment>
            </wsp:All>
            <L7p:assertionComment>
                <L7p:Properties mapValue="included">
                    <L7p:entry>
                        <L7p:key stringValue="LEFT.COMMENT"/>
                        <L7p:value stringValue="Check"/>
                    </L7p:entry>
                    <L7p:entry>
                        <L7p:key stringValue="RIGHT.COMMENT"/>
                        <L7p:value stringValue="Check if a mag identifier is available"/>
                    </L7p:entry>
                </L7p:Properties>
            </L7p:assertionComment>
        </wsp:OneOrMore>
        <wsp:OneOrMore wsp:Usage="Required">
            <wsp:All wsp:Usage="Required">
                <L7p:ComparisonAssertion>
                    <L7p:CaseSensitive booleanValue="false"/>
                    <L7p:Expression1 stringValue="${devicestatus}"/>
                    <L7p:Expression2 stringValue="activated"/>
                    <L7p:MultivaluedComparison multivaluedComparison="FAIL"/>
                    <L7p:Predicates predicates="included">
                        <L7p:item binary="included">
                            <L7p:CaseSensitive booleanValue="false"/>
                            <L7p:RightValue stringValue="activated"/>
                        </L7p:item>
                    </L7p:Predicates>
                </L7p:ComparisonAssertion>
                <L7p:SetVariable>
                    <L7p:Base64Expression stringValue="YWN0aXZhdGVk"/>
                    <L7p:VariableToSet stringValue="devicestatus"/>
                </L7p:SetVariable>
                <L7p:SetVariable>
                    <L7p:Base64Expression stringValue="RU5BQkxFRA=="/>
                    <L7p:VariableToSet stringValue="tokenstatus"/>
                </L7p:SetVariable>
                <L7p:assertionComment>
                    <L7p:Properties mapValue="included">
                        <L7p:entry>
                            <L7p:key stringValue="LEFT.COMMENT"/>
                            <L7p:value stringValue="Enabled"/>
                        </L7p:entry>
                    </L7p:Properties>
                </L7p:assertionComment>
            </wsp:All>
            <wsp:All wsp:Usage="Required">
                <L7p:ComparisonAssertion>
                    <L7p:CaseSensitive booleanValue="false"/>
                    <L7p:Expression1 stringValue="${devicestatus}"/>
                    <L7p:Expression2 stringValue="registered"/>
                    <L7p:MultivaluedComparison multivaluedComparison="FAIL"/>
                    <L7p:Predicates predicates="included">
                        <L7p:item binary="included">
                            <L7p:CaseSensitive booleanValue="false"/>
                            <L7p:RightValue stringValue="registered"/>
                        </L7p:item>
                    </L7p:Predicates>
                </L7p:ComparisonAssertion>
                <L7p:SetVariable>
                    <L7p:Base64Expression stringValue="cmVnaXN0ZXJlZA=="/>
                    <L7p:VariableToSet stringValue="devicestatus"/>
                </L7p:SetVariable>
                <L7p:SetVariable>
                    <L7p:Base64Expression stringValue="RElTQUJMRUQ="/>
                    <L7p:VariableToSet stringValue="tokenstatus"/>
                </L7p:SetVariable>
                <L7p:assertionComment>
                    <L7p:Properties mapValue="included">
                        <L7p:entry>
                            <L7p:key stringValue="LEFT.COMMENT"/>
                            <L7p:value stringValue="Disabled"/>
                        </L7p:entry>
                    </L7p:Properties>
                </L7p:assertionComment>
            </wsp:All>
            <wsp:All wsp:Usage="Required">
                <L7p:SetVariable>
                    <L7p:Base64Expression stringValue="MTAz"/>
                    <L7p:VariableToSet stringValue="error.code"/>
                </L7p:SetVariable>
                <L7p:FalseAssertion/>
                <L7p:assertionComment>
                    <L7p:Properties mapValue="included">
                        <L7p:entry>
                            <L7p:key stringValue="LEFT.COMMENT"/>
                            <L7p:value stringValue="Error"/>
                        </L7p:entry>
                    </L7p:Properties>
                </L7p:assertionComment>
            </wsp:All>
            <L7p:assertionComment>
                <L7p:Properties mapValue="included">
                    <L7p:entry>
                        <L7p:key stringValue="LEFT.COMMENT"/>
                        <L7p:value stringValue="Capitalization"/>
                    </L7p:entry>
                    <L7p:entry>
                        <L7p:key stringValue="RIGHT.COMMENT"/>
                        <L7p:value stringValue="Change status to lower case values AND find the new status for associated access_token"/>
                    </L7p:entry>
                </L7p:Properties>
            </L7p:assertionComment>
        </wsp:OneOrMore>
        <wsp:OneOrMore wsp:Usage="Required">
            <L7p:JdbcQuery>
                <L7p:AssertionComment assertionComment="included">
                    <L7p:Properties mapValue="included">
                        <L7p:entry>
                            <L7p:key stringValue="LEFT.COMMENT"/>
                            <L7p:value stringValue="UPDATE_DEVICE"/>
                        </L7p:entry>
                    </L7p:Properties>
                </L7p:AssertionComment>
                <L7p:ConnectionName stringValue="MAG_OAuth"/>
                <L7p:MaxRecords intValue="1000"/>
                <L7p:QueryTimeout stringValue="0"/>
                <L7p:SqlQuery stringValueReference="inline"><![CDATA[UPDATE mag_msso_device
                SET devicestatus=${devicestatus}
                WHERE magidentifier=${magidentifier}]]></L7p:SqlQuery>
            </L7p:JdbcQuery>
            <wsp:All wsp:Usage="Required">
                <L7p:SetVariable>
                    <L7p:Base64Expression stringValue="MDAw"/>
                    <L7p:VariableToSet stringValue="error.code"/>
                </L7p:SetVariable>
                <L7p:FalseAssertion/>
                <L7p:assertionComment>
                    <L7p:Properties mapValue="included">
                        <L7p:entry>
                            <L7p:key stringValue="LEFT.COMMENT"/>
                            <L7p:value stringValue="Error"/>
                        </L7p:entry>
                    </L7p:Properties>
                </L7p:assertionComment>
            </wsp:All>
            <L7p:assertionComment>
                <L7p:Properties mapValue="included">
                    <L7p:entry>
                        <L7p:key stringValue="LEFT.COMMENT"/>
                        <L7p:value stringValue="Query"/>
                    </L7p:entry>
                </L7p:Properties>
            </L7p:assertionComment>
        </wsp:OneOrMore>
        <wsp:OneOrMore wsp:Usage="Required">
            <L7p:JdbcQuery>
                <L7p:AssertionComment assertionComment="included">
                    <L7p:Properties mapValue="included">
                        <L7p:entry>
                            <L7p:key stringValue="LEFT.COMMENT"/>
                            <L7p:value stringValue="UPDATE_TOKEN"/>
                        </L7p:entry>
                    </L7p:Properties>
                </L7p:AssertionComment>
                <L7p:AssertionFailureEnabled booleanValue="false"/>
                <L7p:ConnectionName stringValue="MAG_OAuth"/>
                <L7p:MaxRecords intValue="1000"/>
                <L7p:QueryTimeout stringValue="0"/>
                <L7p:SqlQuery stringValueReference="inline"><![CDATA[UPDATE oauth_token
                SET oauth_token.status = ${tokenstatus}
                WHERE oauth_token.token IN (
                SELECT mag_device_app.access_token
                FROM mag_device_app
                WHERE mag_device_app.magidentifier = ${magidentifier}
                AND mag_device_app.access_token = oauth_token.token
                )]]></L7p:SqlQuery>
            </L7p:JdbcQuery>
            <L7p:TrueAssertion/>
            <L7p:assertionComment>
                <L7p:Properties mapValue="included">
                    <L7p:entry>
                        <L7p:key stringValue="LEFT.COMMENT"/>
                        <L7p:value stringValue="Token"/>
                    </L7p:entry>
                    <L7p:entry>
                        <L7p:key stringValue="RIGHT.COMMENT"/>
                        <L7p:value stringValue="update access_token IF they are still associated with the device"/>
                    </L7p:entry>
                </L7p:Properties>
            </L7p:assertionComment>
        </wsp:OneOrMore>
        <L7p:SetVariable>
            <L7p:Base64Expression stringValue="dGV4dC9wbGFpbjtjaGFyc2V0PVVURi04"/>
            <L7p:VariableToSet stringValue="content-type"/>
        </L7p:SetVariable>
        <L7p:SetVariable>
            <L7p:Base64Expression stringValue="dXBkYXRlZA=="/>
            <L7p:VariableToSet stringValue="result"/>
        </L7p:SetVariable>
    </wsp:All>
</wsp:Policy>