<?xml version="1.0" encoding="UTF-8"?>
<wsp:Policy xmlns:L7p="http://www.layer7tech.com/ws/policy" xmlns:wsp="http://schemas.xmlsoap.org/ws/2002/12/policy">
    <wsp:All wsp:Usage="Required">
        <L7p:CommentAssertion>
            <L7p:Comment stringValue=" ============================================"/>
        </L7p:CommentAssertion>
        <L7p:CommentAssertion>
            <L7p:Comment stringValue=" === ***  THIS POLICY IS READ ONLY ***"/>
        </L7p:CommentAssertion>
        <L7p:CommentAssertion>
            <L7p:Comment stringValue=" === Required changes can be implemented in policies in the 'Customizations' folder "/>
        </L7p:CommentAssertion>
        <L7p:CommentAssertion>
            <L7p:Comment stringValue=" === The policies within that folder will have the same name as this policy but "/>
        </L7p:CommentAssertion>
        <L7p:CommentAssertion>
            <L7p:Comment stringValue=" === either prefixed with '#' or suffixed with 'Extensions'"/>
        </L7p:CommentAssertion>
        <L7p:CommentAssertion>
            <L7p:Comment stringValue=" === Prefixed policies can be used to overwrite variables of this policy"/>
        </L7p:CommentAssertion>
        <L7p:CommentAssertion>
            <L7p:Comment stringValue=" === Suffixed policies can be used to extend functionality"/>
        </L7p:CommentAssertion>
        <L7p:CommentAssertion>
            <L7p:Comment stringValue=" === If you find you cannot add your customizations using the policies in the 'Customizations' folder"/>
        </L7p:CommentAssertion>
        <L7p:CommentAssertion>
            <L7p:Comment stringValue=" === please contact CA APIM Support so we can improve customization capability"/>
        </L7p:CommentAssertion>
        <L7p:CommentAssertion>
            <L7p:Comment stringValue=" ============================================"/>
        </L7p:CommentAssertion>
        <L7p:CommentAssertion>
            <L7p:Comment stringValue="This fragment should be used as an encapsulated assertion"/>
        </L7p:CommentAssertion>
        <L7p:CommentAssertion>
            <L7p:Comment stringValue="This fragment will authenticate a client certificate against a configuration FIP"/>
        </L7p:CommentAssertion>
        <L7p:CommentAssertion>
            <L7p:Comment stringValue="The fragment will create an error message and an http status code"/>
        </L7p:CommentAssertion>
        <L7p:CommentAssertion>
            <L7p:Comment stringValue="Thie policy should be used at the beginning of a policy after requiring SSL with a client certificate"/>
        </L7p:CommentAssertion>
        <L7p:CommentAssertion>
            <L7p:Comment stringValue="When OTK/MAG gets installed this policy is used at endpoint the the /storage and /ovp folder"/>
        </L7p:CommentAssertion>
        <L7p:CommentAssertion>
            <L7p:Comment stringValue="To implement FIP Authentication, edit the &quot;OTK FIP Client Authentication Extension&quot; policy"/>
        </L7p:CommentAssertion>
        <L7p:Include>
            <L7p:PolicyGuid stringValue="7847c7a6-ac68-456b-841a-122726323efd"/>
        </L7p:Include>
    </wsp:All>
</wsp:Policy>