<?xml version="1.0" encoding="UTF-8"?>
<wsp:Policy xmlns:L7p="http://www.layer7tech.com/ws/policy" xmlns:wsp="http://schemas.xmlsoap.org/ws/2002/12/policy">
    <wsp:All wsp:Usage="Required">
        <L7p:Include>
            <L7p:PolicyGuid stringValue="812ed196-c315-4e92-b630-b5c64c5c043c"/>
        </L7p:Include>
        <L7p:ApiPortalIntegration>
            <L7p:ApiGroup stringValue=""/>
            <L7p:ApiId stringValue="e1f06cfe-7958-4d9c-8d2d-fad09a641502"/>
            <L7p:PortalManagedApiFlag stringValue="L7p:ApiPortalManagedServiceAssertion"/>
        </L7p:ApiPortalIntegration>
        <L7p:Encapsulated>
            <L7p:EncapsulatedAssertionConfigGuid stringValue="8a48ee76-a432-4013-85b6-428c65bd182d"/>
            <L7p:EncapsulatedAssertionConfigName stringValue="API Portal Integration - OAuth 2.0"/>
        </L7p:Encapsulated>
        <wsp:OneOrMore wsp:Usage="Required">
            <wsp:All L7p:Enabled="false" wsp:Usage="Required">
                <L7p:ComparisonAssertion>
                    <L7p:CaseSensitive booleanValue="false"/>
                    <L7p:Expression1 stringValue="${request.http.method}"/>
                    <L7p:Expression2 stringValue="POST"/>
                    <L7p:Predicates predicates="included">
                        <L7p:item binary="included">
                            <L7p:CaseSensitive booleanValue="false"/>
                            <L7p:RightValue stringValue="POST"/>
                        </L7p:item>
                    </L7p:Predicates>
                </L7p:ComparisonAssertion>
                <L7p:assertionComment>
                    <L7p:Properties mapValue="included">
                        <L7p:entry>
                            <L7p:key stringValue="LEFT.COMMENT"/>
                            <L7p:value stringValue="POST"/>
                        </L7p:entry>
                    </L7p:Properties>
                </L7p:assertionComment>
            </wsp:All>
            <wsp:All wsp:Usage="Required">
                <L7p:ComparisonAssertion>
                    <L7p:CaseSensitive booleanValue="false"/>
                    <L7p:Expression1 stringValue="${request.http.method}"/>
                    <L7p:Expression2 stringValue="GET"/>
                    <L7p:Predicates predicates="included">
                        <L7p:item binary="included">
                            <L7p:CaseSensitive booleanValue="false"/>
                            <L7p:RightValue stringValue="GET"/>
                        </L7p:item>
                    </L7p:Predicates>
                </L7p:ComparisonAssertion>
                <L7p:TrueAssertion/>
                <L7p:assertionComment>
                    <L7p:Properties mapValue="included">
                        <L7p:entry>
                            <L7p:key stringValue="LEFT.COMMENT"/>
                            <L7p:value stringValue="GET"/>
                        </L7p:entry>
                    </L7p:Properties>
                </L7p:assertionComment>
            </wsp:All>
            <wsp:All L7p:Enabled="false" wsp:Usage="Required">
                <L7p:ComparisonAssertion>
                    <L7p:CaseSensitive booleanValue="false"/>
                    <L7p:Expression1 stringValue="${request.http.method}"/>
                    <L7p:Expression2 stringValue="PATCH"/>
                    <L7p:Predicates predicates="included">
                        <L7p:item binary="included">
                            <L7p:CaseSensitive booleanValue="false"/>
                            <L7p:RightValue stringValue="PATCH"/>
                        </L7p:item>
                    </L7p:Predicates>
                </L7p:ComparisonAssertion>
                <L7p:assertionComment>
                    <L7p:Properties mapValue="included">
                        <L7p:entry>
                            <L7p:key stringValue="LEFT.COMMENT"/>
                            <L7p:value stringValue="PATCH"/>
                        </L7p:entry>
                    </L7p:Properties>
                </L7p:assertionComment>
            </wsp:All>
            <wsp:All L7p:Enabled="false" wsp:Usage="Required">
                <L7p:ComparisonAssertion>
                    <L7p:CaseSensitive booleanValue="false"/>
                    <L7p:Expression1 stringValue="${request.http.method}"/>
                    <L7p:Expression2 stringValue="PUT"/>
                    <L7p:Predicates predicates="included">
                        <L7p:item binary="included">
                            <L7p:CaseSensitive booleanValue="false"/>
                            <L7p:RightValue stringValue="PUT"/>
                        </L7p:item>
                    </L7p:Predicates>
                </L7p:ComparisonAssertion>
                <L7p:assertionComment>
                    <L7p:Properties mapValue="included">
                        <L7p:entry>
                            <L7p:key stringValue="LEFT.COMMENT"/>
                            <L7p:value stringValue="PUT"/>
                        </L7p:entry>
                    </L7p:Properties>
                </L7p:assertionComment>
            </wsp:All>
            <wsp:All L7p:Enabled="false" wsp:Usage="Required">
                <L7p:ComparisonAssertion>
                    <L7p:CaseSensitive booleanValue="false"/>
                    <L7p:Expression1 stringValue="${request.http.method}"/>
                    <L7p:Expression2 stringValue="DELETE"/>
                    <L7p:Predicates predicates="included">
                        <L7p:item binary="included">
                            <L7p:CaseSensitive booleanValue="false"/>
                            <L7p:RightValue stringValue="DELETE"/>
                        </L7p:item>
                    </L7p:Predicates>
                </L7p:ComparisonAssertion>
                <L7p:assertionComment>
                    <L7p:Properties mapValue="included">
                        <L7p:entry>
                            <L7p:key stringValue="LEFT.COMMENT"/>
                            <L7p:value stringValue="DELETE"/>
                        </L7p:entry>
                    </L7p:Properties>
                </L7p:assertionComment>
            </wsp:All>
            <wsp:All wsp:Usage="Required">
                <L7p:ComparisonAssertion>
                    <L7p:CaseSensitive booleanValue="false"/>
                    <L7p:Expression1 stringValue="${request.http.method}"/>
                    <L7p:Expression2 stringValue="OPTIONS"/>
                    <L7p:Predicates predicates="included">
                        <L7p:item binary="included">
                            <L7p:CaseSensitive booleanValue="false"/>
                            <L7p:RightValue stringValue="OPTIONS"/>
                        </L7p:item>
                    </L7p:Predicates>
                </L7p:ComparisonAssertion>
                <L7p:AddHeader>
                    <L7p:AssertionComment assertionComment="included">
                        <L7p:Properties mapValue="included">
                            <L7p:entry>
                                <L7p:key stringValue="LEFT.COMMENT"/>
                                <L7p:value stringValue="Indicar metodos implementados"/>
                            </L7p:entry>
                        </L7p:Properties>
                    </L7p:AssertionComment>
                    <L7p:HeaderName stringValue="Allow"/>
                    <L7p:HeaderValue stringValue="GET, POST, OPTIONS"/>
                    <L7p:Target target="RESPONSE"/>
                </L7p:AddHeader>
                <L7p:Encapsulated>
                    <L7p:EncapsulatedAssertionConfigGuid stringValue="2873d7c1-bfb2-42b8-ab9a-35767965de80"/>
                    <L7p:EncapsulatedAssertionConfigName stringValue="API Portal Integration - Post Route"/>
                    <L7p:Parameters mapValue="included">
                        <L7p:entry>
                            <L7p:key stringValue="portal.analytics.response.code"/>
                            <L7p:value stringValue="200"/>
                        </L7p:entry>
                        <L7p:entry>
                            <L7p:key stringValue="portal.analytics.routingTotalTime"/>
                            <L7p:value stringValue="${request.elapsedTime}"/>
                        </L7p:entry>
                    </L7p:Parameters>
                </L7p:Encapsulated>
                <L7p:HardcodedResponse>
                    <L7p:ResponseContentType stringValue="application/json; charset=UTF-8"/>
                </L7p:HardcodedResponse>
                <L7p:assertionComment>
                    <L7p:Properties mapValue="included">
                        <L7p:entry>
                            <L7p:key stringValue="LEFT.COMMENT"/>
                            <L7p:value stringValue="OPTIONS"/>
                        </L7p:entry>
                    </L7p:Properties>
                </L7p:assertionComment>
            </wsp:All>
            <wsp:All wsp:Usage="Required">
                <L7p:CustomizeErrorResponse>
                    <L7p:Content stringValue="Method not supported"/>
                    <L7p:ExtraHeaders nameValuePairArray="included">
                        <L7p:item nameValuePair="included">
                            <L7p:Key stringValue="Allow"/>
                            <L7p:Value stringValue="GET, OPTIONS"/>
                        </L7p:item>
                    </L7p:ExtraHeaders>
                    <L7p:HttpStatus stringValue="405"/>
                </L7p:CustomizeErrorResponse>
                <L7p:Encapsulated>
                    <L7p:EncapsulatedAssertionConfigGuid stringValue="2873d7c1-bfb2-42b8-ab9a-35767965de80"/>
                    <L7p:EncapsulatedAssertionConfigName stringValue="API Portal Integration - Post Route"/>
                    <L7p:Parameters mapValue="included">
                        <L7p:entry>
                            <L7p:key stringValue="portal.analytics.response.code"/>
                            <L7p:value stringValue="405"/>
                        </L7p:entry>
                        <L7p:entry>
                            <L7p:key stringValue="portal.analytics.routingTotalTime"/>
                            <L7p:value stringValue="${request.elapsedTime}"/>
                        </L7p:entry>
                    </L7p:Parameters>
                </L7p:Encapsulated>
                <L7p:RaiseError/>
                <L7p:assertionComment>
                    <L7p:Properties mapValue="included">
                        <L7p:entry>
                            <L7p:key stringValue="LEFT.COMMENT"/>
                            <L7p:value stringValue="No soportado"/>
                        </L7p:entry>
                    </L7p:Properties>
                </L7p:assertionComment>
            </wsp:All>
        </wsp:OneOrMore>
        <wsp:All wsp:Usage="Required">
            <wsp:OneOrMore wsp:Usage="Required">
                <wsp:All wsp:Usage="Required">
                    <L7p:HtmlFormDataAssertion>
                        <L7p:AllowGet booleanValue="true"/>
                        <L7p:DisallowOtherFields booleanValue="true"/>
                        <L7p:FieldSpecs htmlFormFieldSpecArray="included">
                            <L7p:item htmlFormFieldSpec="included">
                                <L7p:AllowEmpty boxedBooleanValue="false"/>
                                <L7p:AllowedLocation fieldLocation="requestUrl"/>
                                <L7p:DataType fieldDataType="string"/>
                                <L7p:MaxOccurs intValue="1"/>
                                <L7p:Name stringValue="region"/>
                            </L7p:item>
                            <L7p:item htmlFormFieldSpec="included">
                                <L7p:AllowEmpty boxedBooleanValue="false"/>
                                <L7p:AllowedLocation fieldLocation="requestUrl"/>
                                <L7p:DataType fieldDataType="string"/>
                                <L7p:MaxOccurs intValue="1"/>
                                <L7p:MinOccurs intValue="1"/>
                                <L7p:Name stringValue="serie"/>
                            </L7p:item>
                            <L7p:item htmlFormFieldSpec="included">
                                <L7p:AllowEmpty boxedBooleanValue="false"/>
                                <L7p:AllowedLocation fieldLocation="requestUrl"/>
                                <L7p:DataType fieldDataType="string"/>
                                <L7p:MaxOccurs intValue="1"/>
                                <L7p:MinOccurs intValue="1"/>
                                <L7p:Name stringValue="servicio"/>
                            </L7p:item>
                            <L7p:item htmlFormFieldSpec="included">
                                <L7p:AllowEmpty boxedBooleanValue="false"/>
                                <L7p:AllowedLocation fieldLocation="requestUrl"/>
                                <L7p:DataType fieldDataType="string"/>
                                <L7p:MaxOccurs intValue="1"/>
                                <L7p:MinOccurs intValue="1"/>
                                <L7p:Name stringValue="tipo"/>
                            </L7p:item>
                        </L7p:FieldSpecs>
                    </L7p:HtmlFormDataAssertion>
                </wsp:All>
                <wsp:All wsp:Usage="Required">
                    <L7p:SetVariable>
                        <L7p:Base64Expression stringValue="QTE="/>
                        <L7p:VariableToSet stringValue="code"/>
                    </L7p:SetVariable>
                    <L7p:SetVariable>
                        <L7p:Base64Expression stringValue="SW52YWxpZCBwYXJhbWV0ZXI="/>
                        <L7p:VariableToSet stringValue="description"/>
                    </L7p:SetVariable>
                    <L7p:SetVariable>
                        <L7p:Base64Expression stringValue="Rm9ybWF0byBkZSBwYXLDoW1ldHJvIGludmFsaWRv"/>
                        <L7p:VariableToSet stringValue="descriptionDetail"/>
                    </L7p:SetVariable>
                    <L7p:AuditDetailAssertion>
                        <L7p:CustomLoggerSuffix stringValue="entel.api.syslog"/>
                        <L7p:Detail stringValue="IDTRANSACTION: ${requestId} CODE: ${code} DESCRIPTION: ${description} DETAIL: ${descriptionDetail}"/>
                        <L7p:LoggingOnly booleanValue="true"/>
                    </L7p:AuditDetailAssertion>
                    <L7p:SetVariable>
                        <L7p:Base64Expression stringValue="JHtyZXF1ZXN0LnRpbWUubG9jYWwueXl5eS9NTS9kZCdUJ0hIOm1tOnNzLlNTU30="/>
                        <L7p:VariableToSet stringValue="responseTimestamp"/>
                    </L7p:SetVariable>
                    <L7p:CustomizeErrorResponse>
                        <L7p:Content stringValueReference="inline"><![CDATA[{
"result":{
	"transactionId":"${requestId}",
	"code":"${code}",
	"description":"${description}",
	"descriptionDetail":"${descriptionDetail}",
	"responseTimestamp":"${responseTimestamp}"
	}
}]]></L7p:Content>
                        <L7p:ContentType stringValue="application/json; charset=UTF-8"/>
                        <L7p:ExtraHeaders nameValuePairArray="included"/>
                        <L7p:HttpStatus stringValue="200"/>
                    </L7p:CustomizeErrorResponse>
                    <L7p:Encapsulated>
                        <L7p:EncapsulatedAssertionConfigGuid stringValue="2873d7c1-bfb2-42b8-ab9a-35767965de80"/>
                        <L7p:EncapsulatedAssertionConfigName stringValue="API Portal Integration - Post Route"/>
                        <L7p:Parameters mapValue="included">
                            <L7p:entry>
                                <L7p:key stringValue="portal.analytics.response.code"/>
                                <L7p:value stringValue="200"/>
                            </L7p:entry>
                            <L7p:entry>
                                <L7p:key stringValue="portal.analytics.routingTotalTime"/>
                                <L7p:value stringValue="${request.elapsedTime}"/>
                            </L7p:entry>
                        </L7p:Parameters>
                    </L7p:Encapsulated>
                    <L7p:RaiseError/>
                </wsp:All>
                <L7p:assertionComment>
                    <L7p:Properties mapValue="included">
                        <L7p:entry>
                            <L7p:key stringValue="RIGHT.COMMENT"/>
                            <L7p:value stringValue="validar query uri"/>
                        </L7p:entry>
                    </L7p:Properties>
                </L7p:assertionComment>
            </wsp:OneOrMore>
            <wsp:OneOrMore wsp:Usage="Required">
                <wsp:All wsp:Usage="Required">
                    <L7p:SetVariable>
                        <L7p:Base64Expression stringValue="JHtyZXF1ZXN0Lmh0dHAucGFyYW1ldGVyLnRpcG99"/>
                        <L7p:VariableToSet stringValue="tipoConsulta"/>
                    </L7p:SetVariable>
                    <wsp:OneOrMore wsp:Usage="Required">
                        <L7p:ComparisonAssertion>
                            <L7p:CaseSensitive booleanValue="false"/>
                            <L7p:Expression1 stringValue="${tipoConsulta}"/>
                            <L7p:Operator operatorNull="null"/>
                            <L7p:Predicates predicates="included">
                                <L7p:item dataType="included">
                                    <L7p:Type variableDataType="string"/>
                                </L7p:item>
                                <L7p:item binary="included">
                                    <L7p:CaseSensitive booleanValue="false"/>
                                    <L7p:RightValue stringValue="region"/>
                                </L7p:item>
                            </L7p:Predicates>
                        </L7p:ComparisonAssertion>
                        <L7p:ComparisonAssertion>
                            <L7p:CaseSensitive booleanValue="false"/>
                            <L7p:Expression1 stringValue="${tipoConsulta}"/>
                            <L7p:Operator operatorNull="null"/>
                            <L7p:Predicates predicates="included">
                                <L7p:item dataType="included">
                                    <L7p:Type variableDataType="string"/>
                                </L7p:item>
                                <L7p:item binary="included">
                                    <L7p:CaseSensitive booleanValue="false"/>
                                    <L7p:RightValue stringValue="comuna"/>
                                </L7p:item>
                            </L7p:Predicates>
                        </L7p:ComparisonAssertion>
                    </wsp:OneOrMore>
                    <wsp:OneOrMore wsp:Usage="Required">
                        <wsp:All wsp:Usage="Required">
                            <L7p:ComparisonAssertion>
                                <L7p:CaseSensitive booleanValue="false"/>
                                <L7p:Expression1 stringValue="${tipoConsulta}"/>
                                <L7p:Operator operatorNull="null"/>
                                <L7p:Predicates predicates="included">
                                    <L7p:item dataType="included">
                                    <L7p:Type variableDataType="string"/>
                                    </L7p:item>
                                    <L7p:item binary="included">
                                    <L7p:CaseSensitive booleanValue="false"/>
                                    <L7p:RightValue stringValue="comuna"/>
                                    </L7p:item>
                                </L7p:Predicates>
                            </L7p:ComparisonAssertion>
                            <L7p:HtmlFormDataAssertion>
                                <L7p:AllowGet booleanValue="true"/>
                                <L7p:FieldSpecs htmlFormFieldSpecArray="included">
                                    <L7p:item htmlFormFieldSpec="included">
                                    <L7p:AllowEmpty boxedBooleanValue="false"/>
                                    <L7p:AllowedLocation fieldLocation="requestUrl"/>
                                    <L7p:DataType fieldDataType="string"/>
                                    <L7p:MaxOccurs intValue="1"/>
                                    <L7p:MinOccurs intValue="1"/>
                                    <L7p:Name stringValue="region"/>
                                    </L7p:item>
                                </L7p:FieldSpecs>
                            </L7p:HtmlFormDataAssertion>
                            <L7p:TrueAssertion/>
                        </wsp:All>
                        <wsp:All wsp:Usage="Required">
                            <L7p:ComparisonAssertion>
                                <L7p:CaseSensitive booleanValue="false"/>
                                <L7p:Expression1 stringValue="${tipoConsulta}"/>
                                <L7p:Operator operatorNull="null"/>
                                <L7p:Predicates predicates="included">
                                    <L7p:item dataType="included">
                                    <L7p:Type variableDataType="string"/>
                                    </L7p:item>
                                    <L7p:item binary="included">
                                    <L7p:CaseSensitive booleanValue="false"/>
                                    <L7p:RightValue stringValue="region"/>
                                    </L7p:item>
                                </L7p:Predicates>
                            </L7p:ComparisonAssertion>
                            <L7p:TrueAssertion/>
                        </wsp:All>
                        <wsp:All wsp:Usage="Required">
                            <L7p:SetVariable>
                                <L7p:Base64Expression stringValue="QTE="/>
                                <L7p:VariableToSet stringValue="code"/>
                            </L7p:SetVariable>
                            <L7p:SetVariable>
                                <L7p:Base64Expression stringValue="SW52YWxpZCBwYXJhbWV0ZXI="/>
                                <L7p:VariableToSet stringValue="description"/>
                            </L7p:SetVariable>
                            <L7p:SetVariable>
                                <L7p:Base64Expression stringValue="UGFyw6FtZXRybyByZWdpb24gZXMgcmVxdWVyaWRv"/>
                                <L7p:VariableToSet stringValue="descriptionDetail"/>
                            </L7p:SetVariable>
                            <L7p:AuditDetailAssertion>
                                <L7p:CustomLoggerSuffix stringValue="entel.api.syslog"/>
                                <L7p:Detail stringValue="IDTRANSACTION: ${requestId} CODE: ${code} DESCRIPTION: ${description} DETAIL: ${descriptionDetail}"/>
                                <L7p:LoggingOnly booleanValue="true"/>
                            </L7p:AuditDetailAssertion>
                            <L7p:SetVariable>
                                <L7p:Base64Expression stringValue="JHtyZXF1ZXN0LnRpbWUubG9jYWwueXl5eS9NTS9kZCdUJ0hIOm1tOnNzLlNTU30="/>
                                <L7p:VariableToSet stringValue="responseTimestamp"/>
                            </L7p:SetVariable>
                            <L7p:CustomizeErrorResponse>
                                <L7p:Content stringValueReference="inline"><![CDATA[{
"result":{
	"transactionId":"${requestId}",
	"code":"${code}",
	"description":"${description}",
	"descriptionDetail":"${descriptionDetail}",
	"responseTimestamp":"${responseTimestamp}"
	}
}]]></L7p:Content>
                                <L7p:ContentType stringValue="application/json; charset=UTF-8"/>
                                <L7p:ExtraHeaders nameValuePairArray="included"/>
                                <L7p:HttpStatus stringValue="200"/>
                            </L7p:CustomizeErrorResponse>
                            <L7p:Encapsulated>
                                <L7p:EncapsulatedAssertionConfigGuid stringValue="2873d7c1-bfb2-42b8-ab9a-35767965de80"/>
                                <L7p:EncapsulatedAssertionConfigName stringValue="API Portal Integration - Post Route"/>
                                <L7p:Parameters mapValue="included">
                                    <L7p:entry>
                                    <L7p:key stringValue="portal.analytics.response.code"/>
                                    <L7p:value stringValue="200"/>
                                    </L7p:entry>
                                    <L7p:entry>
                                    <L7p:key stringValue="portal.analytics.routingTotalTime"/>
                                    <L7p:value stringValue="${request.elapsedTime}"/>
                                    </L7p:entry>
                                </L7p:Parameters>
                            </L7p:Encapsulated>
                            <L7p:RaiseError/>
                        </wsp:All>
                    </wsp:OneOrMore>
                </wsp:All>
                <wsp:All wsp:Usage="Required">
                    <L7p:SetVariable>
                        <L7p:Base64Expression stringValue="QTE="/>
                        <L7p:VariableToSet stringValue="code"/>
                    </L7p:SetVariable>
                    <L7p:SetVariable>
                        <L7p:Base64Expression stringValue="SW52YWxpZCBwYXJhbWV0ZXI="/>
                        <L7p:VariableToSet stringValue="description"/>
                    </L7p:SetVariable>
                    <L7p:SetVariable>
                        <L7p:Base64Expression stringValue="UGFyw6FtZXRybyB0aXBvIHNvbG8gcHVlZGUgdGVuZXIgbG9zIHZhbG9yZXMgcmVnaW9uIG8gY29tdW5h"/>
                        <L7p:VariableToSet stringValue="descriptionDetail"/>
                    </L7p:SetVariable>
                    <L7p:AuditDetailAssertion>
                        <L7p:CustomLoggerSuffix stringValue="entel.api.syslog"/>
                        <L7p:Detail stringValue="IDTRANSACTION: ${requestId} CODE: ${code} DESCRIPTION: ${description} DETAIL: ${descriptionDetail}"/>
                        <L7p:LoggingOnly booleanValue="true"/>
                    </L7p:AuditDetailAssertion>
                    <L7p:SetVariable>
                        <L7p:Base64Expression stringValue="JHtyZXF1ZXN0LnRpbWUubG9jYWwueXl5eS9NTS9kZCdUJ0hIOm1tOnNzLlNTU30="/>
                        <L7p:VariableToSet stringValue="responseTimestamp"/>
                    </L7p:SetVariable>
                    <L7p:CustomizeErrorResponse>
                        <L7p:Content stringValueReference="inline"><![CDATA[{
"result":{
	"transactionId":"${requestId}",
	"code":"${code}",
	"description":"${description}",
	"descriptionDetail":"${descriptionDetail}",
	"responseTimestamp":"${responseTimestamp}"
	}
}]]></L7p:Content>
                        <L7p:ContentType stringValue="application/json; charset=UTF-8"/>
                        <L7p:ExtraHeaders nameValuePairArray="included"/>
                        <L7p:HttpStatus stringValue="200"/>
                    </L7p:CustomizeErrorResponse>
                    <L7p:Encapsulated>
                        <L7p:EncapsulatedAssertionConfigGuid stringValue="2873d7c1-bfb2-42b8-ab9a-35767965de80"/>
                        <L7p:EncapsulatedAssertionConfigName stringValue="API Portal Integration - Post Route"/>
                        <L7p:Parameters mapValue="included">
                            <L7p:entry>
                                <L7p:key stringValue="portal.analytics.response.code"/>
                                <L7p:value stringValue="200"/>
                            </L7p:entry>
                            <L7p:entry>
                                <L7p:key stringValue="portal.analytics.routingTotalTime"/>
                                <L7p:value stringValue="${request.elapsedTime}"/>
                            </L7p:entry>
                        </L7p:Parameters>
                    </L7p:Encapsulated>
                    <L7p:RaiseError/>
                </wsp:All>
            </wsp:OneOrMore>
        </wsp:All>
        <wsp:OneOrMore wsp:Usage="Required">
            <wsp:All wsp:Usage="Required">
                <L7p:ComparisonAssertion>
                    <L7p:CaseSensitive booleanValue="false"/>
                    <L7p:Expression1 stringValue="${tipoConsulta}"/>
                    <L7p:Operator operatorNull="null"/>
                    <L7p:Predicates predicates="included">
                        <L7p:item dataType="included">
                            <L7p:Type variableDataType="string"/>
                        </L7p:item>
                        <L7p:item binary="included">
                            <L7p:CaseSensitive booleanValue="false"/>
                            <L7p:RightValue stringValue="comuna"/>
                        </L7p:item>
                    </L7p:Predicates>
                </L7p:ComparisonAssertion>
                <wsp:OneOrMore wsp:Usage="Required">
                    <wsp:All wsp:Usage="Required">
                        <L7p:SetVariable>
                            <L7p:Base64Expression stringValue="PHNvYXBlbnY6RW52ZWxvcGUgeG1sbnM6c29hcGVudj0iaHR0cDovL3NjaGVtYXMueG1sc29hcC5vcmcvc29hcC9lbnZlbG9wZS8iIHhtbG5zOnR5cGU9Imh0dHA6Ly93d3cuZXNhLmNvbS9DUk0vQ2VudGVyQWRtaW5pc3RyYXRpb24vVC9MaXN0YXJDb211bmFPZmljaW5hT3BlcmF0aXZhL3R5cGUiPg0KICAgPHNvYXBlbnY6SGVhZGVyLz4NCiAgIDxzb2FwZW52OkJvZHk+DQogICAgICA8dHlwZTpMaXN0YXJDb211bmFSZWdpb25PZmljaW5hUmVxdWVzdD4NCiAgICAgICAgIDwhLS1PcHRpb25hbDotLT4NCiAgICAgICAgIDx0eXBlOkNPRElfU0VSSUU+JHtyZXF1ZXN0Lmh0dHAucGFyYW1ldGVyLnNlcmllfTwvdHlwZTpDT0RJX1NFUklFPg0KICAgICAgICAgPCEtLU9wdGlvbmFsOi0tPg0KICAgICAgICAgPHR5cGU6Q09ESV9SRUdJT04+JHtyZXF1ZXN0Lmh0dHAucGFyYW1ldGVyLnJlZ2lvbn08L3R5cGU6Q09ESV9SRUdJT04+DQogICAgICAgICA8IS0tT3B0aW9uYWw6LS0+DQogICAgICAgICA8dHlwZTpUSVBPX1NFUlZJQ0lPPiR7cmVxdWVzdC5odHRwLnBhcmFtZXRlci5zZXJ2aWNpb308L3R5cGU6VElQT19TRVJWSUNJTz4NCiAgICAgIDwvdHlwZTpMaXN0YXJDb211bmFSZWdpb25PZmljaW5hUmVxdWVzdD4NCiAgIDwvc29hcGVudjpCb2R5Pg0KPC9zb2FwZW52OkVudmVsb3BlPg=="/>
                            <L7p:ContentType stringValue="text/xml; charset=utf-8"/>
                            <L7p:DataType variableDataType="message"/>
                            <L7p:VariableToSet stringValue="requestComuna"/>
                        </L7p:SetVariable>
                        <L7p:HttpRoutingAssertion>
                            <L7p:ConnectionTimeout stringValue="3000"/>
                            <L7p:FailOnErrorStatus booleanValue="false"/>
                            <L7p:HttpMethod httpMethod="POST"/>
                            <L7p:MaxRetries intValue="2"/>
                            <L7p:ProtectedServiceUrl stringValue="http://${gateway.esb.hostname}/crm/centeradministration/centerproductivitymgmt/crm_t_px_listarcomunaoficinaoperativaps?wsdl"/>
                            <L7p:ProxyPassword stringValueNull="null"/>
                            <L7p:ProxyUsername stringValueNull="null"/>
                            <L7p:RequestHeaderRules httpPassthroughRuleSet="included">
                                <L7p:ForwardAll booleanValue="true"/>
                                <L7p:Rules httpPassthroughRules="included">
                                    <L7p:item httpPassthroughRule="included">
                                    <L7p:Name stringValue="Cookie"/>
                                    </L7p:item>
                                    <L7p:item httpPassthroughRule="included">
                                    <L7p:Name stringValue="SOAPAction"/>
                                    </L7p:item>
                                </L7p:Rules>
                            </L7p:RequestHeaderRules>
                            <L7p:RequestMsgSrc stringValue="requestComuna"/>
                            <L7p:RequestParamRules httpPassthroughRuleSet="included">
                                <L7p:ForwardAll booleanValue="true"/>
                                <L7p:Rules httpPassthroughRules="included"/>
                            </L7p:RequestParamRules>
                            <L7p:ResponseHeaderRules httpPassthroughRuleSet="included">
                                <L7p:ForwardAll booleanValue="true"/>
                                <L7p:Rules httpPassthroughRules="included">
                                    <L7p:item httpPassthroughRule="included">
                                    <L7p:Name stringValue="Set-Cookie"/>
                                    </L7p:item>
                                </L7p:Rules>
                            </L7p:ResponseHeaderRules>
                            <L7p:ResponseMsgDest stringValue="serviceResponse"/>
                            <L7p:SamlAssertionVersion intValue="2"/>
                        </L7p:HttpRoutingAssertion>
                    </wsp:All>
                </wsp:OneOrMore>
            </wsp:All>
            <wsp:All wsp:Usage="Required">
                <L7p:ComparisonAssertion>
                    <L7p:CaseSensitive booleanValue="false"/>
                    <L7p:Expression1 stringValue="${tipoConsulta}"/>
                    <L7p:Operator operatorNull="null"/>
                    <L7p:Predicates predicates="included">
                        <L7p:item dataType="included">
                            <L7p:Type variableDataType="string"/>
                        </L7p:item>
                        <L7p:item binary="included">
                            <L7p:CaseSensitive booleanValue="false"/>
                            <L7p:RightValue stringValue="region"/>
                        </L7p:item>
                    </L7p:Predicates>
                </L7p:ComparisonAssertion>
                <wsp:OneOrMore wsp:Usage="Required">
                    <wsp:All wsp:Usage="Required">
                        <L7p:SetVariable>
                            <L7p:Base64Expression stringValue="PHNvYXBlbnY6RW52ZWxvcGUgeG1sbnM6c29hcGVudj0iaHR0cDovL3NjaGVtYXMueG1sc29hcC5vcmcvc29hcC9lbnZlbG9wZS8iIHhtbG5zOnR5cGU9Imh0dHA6Ly93d3cuZXNhLmNvbS9DUk0vQ2VudGVyQWRtaW5pc3RyYXRpb24vVC9MaXN0YXJSZWdpb25PZmljaW5hT3BlcmF0aXZhL3R5cGUiPg0KICAgPHNvYXBlbnY6SGVhZGVyLz4NCiAgIDxzb2FwZW52OkJvZHk+DQogICAgICA8dHlwZTpMaXN0YXJSZWdpb25PZmljaW5hUmVxdWVzdD4NCiAgICAgICAgIDwhLS1PcHRpb25hbDotLT4NCiAgICAgICAgIDx0eXBlOkNPRElfU0VSSUU+JHtyZXF1ZXN0Lmh0dHAucGFyYW1ldGVyLnNlcmllfTwvdHlwZTpDT0RJX1NFUklFPg0KICAgICAgICAgPCEtLU9wdGlvbmFsOi0tPg0KICAgICAgICAgPHR5cGU6VElQT19TRVJWSUNJTz4ke3JlcXVlc3QuaHR0cC5wYXJhbWV0ZXIuc2VydmljaW99PC90eXBlOlRJUE9fU0VSVklDSU8+DQogICAgICA8L3R5cGU6TGlzdGFyUmVnaW9uT2ZpY2luYVJlcXVlc3Q+DQogICA8L3NvYXBlbnY6Qm9keT4NCjwvc29hcGVudjpFbnZlbG9wZT4="/>
                            <L7p:ContentType stringValue="text/xml; charset=utf-8"/>
                            <L7p:DataType variableDataType="message"/>
                            <L7p:VariableToSet stringValue="requestRegion"/>
                        </L7p:SetVariable>
                        <L7p:HttpRoutingAssertion>
                            <L7p:ConnectionTimeout stringValue="3000"/>
                            <L7p:FailOnErrorStatus booleanValue="false"/>
                            <L7p:HttpMethod httpMethod="POST"/>
                            <L7p:MaxRetries intValue="2"/>
                            <L7p:ProtectedServiceUrl stringValue="http://${gateway.esb.hostname}/crm/centeradministration/centerproductivitymgmt/crm_t_px_listarregionoficinaoperativaps?wsdl"/>
                            <L7p:ProxyPassword stringValueNull="null"/>
                            <L7p:ProxyUsername stringValueNull="null"/>
                            <L7p:RequestHeaderRules httpPassthroughRuleSet="included">
                                <L7p:ForwardAll booleanValue="true"/>
                                <L7p:Rules httpPassthroughRules="included">
                                    <L7p:item httpPassthroughRule="included">
                                    <L7p:Name stringValue="Cookie"/>
                                    </L7p:item>
                                    <L7p:item httpPassthroughRule="included">
                                    <L7p:Name stringValue="SOAPAction"/>
                                    </L7p:item>
                                </L7p:Rules>
                            </L7p:RequestHeaderRules>
                            <L7p:RequestMsgSrc stringValue="requestRegion"/>
                            <L7p:RequestParamRules httpPassthroughRuleSet="included">
                                <L7p:ForwardAll booleanValue="true"/>
                                <L7p:Rules httpPassthroughRules="included"/>
                            </L7p:RequestParamRules>
                            <L7p:ResponseHeaderRules httpPassthroughRuleSet="included">
                                <L7p:ForwardAll booleanValue="true"/>
                                <L7p:Rules httpPassthroughRules="included">
                                    <L7p:item httpPassthroughRule="included">
                                    <L7p:Name stringValue="Set-Cookie"/>
                                    </L7p:item>
                                </L7p:Rules>
                            </L7p:ResponseHeaderRules>
                            <L7p:ResponseMsgDest stringValue="serviceResponse"/>
                            <L7p:SamlAssertionVersion intValue="2"/>
                        </L7p:HttpRoutingAssertion>
                    </wsp:All>
                </wsp:OneOrMore>
            </wsp:All>
        </wsp:OneOrMore>
        <wsp:OneOrMore wsp:Usage="Required">
            <wsp:All wsp:Usage="Required">
                <L7p:ComparisonAssertion>
                    <L7p:CaseSensitive booleanValue="false"/>
                    <L7p:Expression1 stringValue="${httpRouting.reasonCode}"/>
                    <L7p:Operator operatorNull="null"/>
                    <L7p:Predicates predicates="included">
                        <L7p:item dataType="included">
                            <L7p:Type variableDataType="int"/>
                        </L7p:item>
                        <L7p:item binary="included">
                            <L7p:CaseSensitive booleanValue="false"/>
                            <L7p:RightValue stringValue="200"/>
                        </L7p:item>
                    </L7p:Predicates>
                </L7p:ComparisonAssertion>
                <L7p:Include>
                    <L7p:PolicyGuid stringValue="6ca99a73-dddf-4d5c-b579-1b8ff18635d6"/>
                </L7p:Include>
                <L7p:SetVariable>
                    <L7p:Base64Expression stringValue="JHtzZXJ2aWNlUmVzcG9uc2UubWFpbnBhcnR9"/>
                    <L7p:ContentType stringValue="application/json; charset=utf-8"/>
                    <L7p:DataType variableDataType="message"/>
                    <L7p:VariableToSet stringValue="responseJson"/>
                </L7p:SetVariable>
                <wsp:OneOrMore wsp:Usage="Required">
                    <wsp:All wsp:Usage="Required">
                        <L7p:ComparisonAssertion>
                            <L7p:CaseSensitive booleanValue="false"/>
                            <L7p:Expression1 stringValue="${tipoConsulta}"/>
                            <L7p:Operator operatorNull="null"/>
                            <L7p:Predicates predicates="included">
                                <L7p:item dataType="included">
                                    <L7p:Type variableDataType="string"/>
                                </L7p:item>
                                <L7p:item binary="included">
                                    <L7p:CaseSensitive booleanValue="false"/>
                                    <L7p:RightValue stringValue="comuna"/>
                                </L7p:item>
                            </L7p:Predicates>
                        </L7p:ComparisonAssertion>
                        <L7p:EvaluateJsonPathExpression>
                            <L7p:Expression stringValue="$.Envelope.Body.ListarComunaRegionOficinaResponse.O_COD"/>
                            <L7p:OtherTargetMessageVariable stringValue="responseJson"/>
                            <L7p:Target target="OTHER"/>
                            <L7p:VariablePrefix stringValue="countData"/>
                        </L7p:EvaluateJsonPathExpression>
                        <wsp:OneOrMore wsp:Usage="Required">
                            <wsp:All wsp:Usage="Required">
                                <L7p:ComparisonAssertion>
                                    <L7p:CaseSensitive booleanValue="false"/>
                                    <L7p:Expression1 stringValue="${countData.result}"/>
                                    <L7p:Expression2 stringValue="0"/>
                                    <L7p:Predicates predicates="included">
                                    <L7p:item binary="included">
                                    <L7p:CaseSensitive booleanValue="false"/>
                                    <L7p:RightValue stringValue="0"/>
                                    </L7p:item>
                                    </L7p:Predicates>
                                </L7p:ComparisonAssertion>
                                <L7p:EvaluateJsonPathExpression>
                                    <L7p:Expression stringValue="$.Envelope.Body.ListarComunaRegionOficinaResponse.COMUNAS"/>
                                    <L7p:OtherTargetMessageVariable stringValue="responseJson"/>
                                    <L7p:Target target="OTHER"/>
                                </L7p:EvaluateJsonPathExpression>
                                <L7p:SetVariable>
                                    <L7p:Base64Expression stringValue="JHtqc29uUGF0aC5yZXN1bHRzfQ=="/>
                                    <L7p:VariableToSet stringValue="comunasJson"/>
                                </L7p:SetVariable>
                                <L7p:Regex>
                                    <L7p:AutoTarget booleanValue="false"/>
                                    <L7p:OtherTargetMessageVariable stringValue="comunasJson"/>
                                    <L7p:Regex stringValue="CODI_COMUNA"/>
                                    <L7p:Replace booleanValue="true"/>
                                    <L7p:Replacement stringValue="codi_territorio"/>
                                    <L7p:Target target="OTHER"/>
                                </L7p:Regex>
                                <L7p:Regex>
                                    <L7p:AutoTarget booleanValue="false"/>
                                    <L7p:OtherTargetMessageVariable stringValue="comunasJson"/>
                                    <L7p:Regex stringValue="NOM_COMUNA"/>
                                    <L7p:Replace booleanValue="true"/>
                                    <L7p:Replacement stringValue="nom_territorio"/>
                                    <L7p:Target target="OTHER"/>
                                </L7p:Regex>
                                <L7p:SetVariable>
                                    <L7p:Base64Expression stringValue="ImNvZCI6IiR7Y291bnREYXRhLnJlc3VsdH0iLA0KInRlcnJpdG9yaW8iOlske2NvbXVuYXNKc29ufV0="/>
                                    <L7p:VariableToSet stringValue="body"/>
                                </L7p:SetVariable>
                                <L7p:SetVariable>
                                    <L7p:Base64Expression stringValue="MjAw"/>
                                    <L7p:VariableToSet stringValue="code"/>
                                </L7p:SetVariable>
                                <L7p:SetVariable>
                                    <L7p:Base64Expression stringValue="U3VjY2Vzc2Z1bCBvcGVyYXRpb24="/>
                                    <L7p:VariableToSet stringValue="description"/>
                                </L7p:SetVariable>
                                <L7p:SetVariable>
                                    <L7p:Base64Expression stringValue="U3VjY2Vzc2Z1bCBvcGVyYXRpb24="/>
                                    <L7p:VariableToSet stringValue="descriptionDetail"/>
                                </L7p:SetVariable>
                                <L7p:SetVariable>
                                    <L7p:Base64Expression stringValue="JHtyZXF1ZXN0LnRpbWUubG9jYWwueXl5eS9NTS9kZCdUJ0hIOm1tOnNzLlNTU30="/>
                                    <L7p:VariableToSet stringValue="responseTimestamp"/>
                                </L7p:SetVariable>
                                <L7p:Encapsulated>
                                    <L7p:EncapsulatedAssertionConfigGuid stringValue="2873d7c1-bfb2-42b8-ab9a-35767965de80"/>
                                    <L7p:EncapsulatedAssertionConfigName stringValue="API Portal Integration - Post Route"/>
                                    <L7p:Parameters mapValue="included">
                                    <L7p:entry>
                                    <L7p:key stringValue="portal.analytics.response.code"/>
                                    <L7p:value stringValue="200"/>
                                    </L7p:entry>
                                    <L7p:entry>
                                    <L7p:key stringValue="portal.analytics.routingTotalTime"/>
                                    <L7p:value stringValue="${request.elapsedTime}"/>
                                    </L7p:entry>
                                    </L7p:Parameters>
                                </L7p:Encapsulated>
                                <L7p:HardcodedResponse>
                                    <L7p:Base64ResponseBody stringValue="ewoicmVzdWx0Ijp7CgkidHJhbnNhY3Rpb25JZCI6IiR7cmVxdWVzdElkfSIsCgkiY29kZSI6IiR7Y29kZX0iLAoJImRlc2NyaXB0aW9uIjoiJHtkZXNjcmlwdGlvbn0iLAoJInJlc3BvbnNlVGltZXN0YW1wIjoiJHtyZXNwb25zZVRpbWVzdGFtcH0iCgl9LAoke2JvZHl9Cn0="/>
                                    <L7p:ResponseContentType stringValue="application/json; charset=UTF-8"/>
                                </L7p:HardcodedResponse>
                            </wsp:All>
                            <wsp:All wsp:Usage="Required">
                                <L7p:ComparisonAssertion>
                                    <L7p:CaseSensitive booleanValue="false"/>
                                    <L7p:Expression1 stringValue="${countData.result}"/>
                                    <L7p:Expression2 stringValue="1"/>
                                    <L7p:Predicates predicates="included">
                                    <L7p:item binary="included">
                                    <L7p:CaseSensitive booleanValue="false"/>
                                    <L7p:RightValue stringValue="1"/>
                                    </L7p:item>
                                    </L7p:Predicates>
                                </L7p:ComparisonAssertion>
                                <L7p:EvaluateJsonPathExpression>
                                    <L7p:Expression stringValue="$.Envelope.Body.ListarComunaRegionOficinaResponse.O_DESC"/>
                                    <L7p:OtherTargetMessageVariable stringValue="responseJson"/>
                                    <L7p:Target target="OTHER"/>
                                    <L7p:VariablePrefix stringValue="descriptionData"/>
                                </L7p:EvaluateJsonPathExpression>
                                <L7p:SetVariable>
                                    <L7p:Base64Expression stringValue="MjAw"/>
                                    <L7p:VariableToSet stringValue="code"/>
                                </L7p:SetVariable>
                                <L7p:SetVariable>
                                    <L7p:Base64Expression stringValue="U3VjY2Vzc2Z1bCBvcGVyYXRpb24="/>
                                    <L7p:VariableToSet stringValue="description"/>
                                </L7p:SetVariable>
                                <L7p:SetVariable>
                                    <L7p:Base64Expression stringValue="U3VjY2Vzc2Z1bCBvcGVyYXRpb24="/>
                                    <L7p:VariableToSet stringValue="descriptionDetail"/>
                                </L7p:SetVariable>
                                <L7p:SetVariable>
                                    <L7p:Base64Expression stringValue="JHtyZXF1ZXN0LnRpbWUubG9jYWwueXl5eS9NTS9kZCdUJ0hIOm1tOnNzLlNTU30="/>
                                    <L7p:VariableToSet stringValue="responseTimestamp"/>
                                </L7p:SetVariable>
                                <L7p:SetVariable>
                                    <L7p:Base64Expression stringValue="ImNvZCI6IiR7Y291bnREYXRhLnJlc3VsdH0iLA0KImRlc2NyaXB0aW9uIjoiJHtkZXNjcmlwdGlvbkRhdGEucmVzdWx0fSI="/>
                                    <L7p:VariableToSet stringValue="body"/>
                                </L7p:SetVariable>
                                <L7p:Encapsulated>
                                    <L7p:EncapsulatedAssertionConfigGuid stringValue="2873d7c1-bfb2-42b8-ab9a-35767965de80"/>
                                    <L7p:EncapsulatedAssertionConfigName stringValue="API Portal Integration - Post Route"/>
                                    <L7p:Parameters mapValue="included">
                                    <L7p:entry>
                                    <L7p:key stringValue="portal.analytics.response.code"/>
                                    <L7p:value stringValue="200"/>
                                    </L7p:entry>
                                    <L7p:entry>
                                    <L7p:key stringValue="portal.analytics.routingTotalTime"/>
                                    <L7p:value stringValue="${request.elapsedTime}"/>
                                    </L7p:entry>
                                    </L7p:Parameters>
                                </L7p:Encapsulated>
                                <L7p:HardcodedResponse>
                                    <L7p:Base64ResponseBody stringValue="ewoicmVzdWx0Ijp7CgkidHJhbnNhY3Rpb25JZCI6IiR7cmVxdWVzdElkfSIsCgkiY29kZSI6IiR7Y29kZX0iLAoJImRlc2NyaXB0aW9uIjoiJHtkZXNjcmlwdGlvbn0iLAoJInJlc3BvbnNlVGltZXN0YW1wIjoiJHtyZXNwb25zZVRpbWVzdGFtcH0iCgl9LAoke2JvZHl9Cn0="/>
                                    <L7p:ResponseContentType stringValue="application/json; charset=UTF-8"/>
                                </L7p:HardcodedResponse>
                            </wsp:All>
                        </wsp:OneOrMore>
                        <L7p:assertionComment>
                            <L7p:Properties mapValue="included">
                                <L7p:entry>
                                    <L7p:key stringValue="RIGHT.COMMENT"/>
                                    <L7p:value stringValue="generar respuesta para comuna"/>
                                </L7p:entry>
                            </L7p:Properties>
                        </L7p:assertionComment>
                    </wsp:All>
                    <wsp:All wsp:Usage="Required">
                        <L7p:ComparisonAssertion>
                            <L7p:CaseSensitive booleanValue="false"/>
                            <L7p:Expression1 stringValue="${tipoConsulta}"/>
                            <L7p:Operator operatorNull="null"/>
                            <L7p:Predicates predicates="included">
                                <L7p:item dataType="included">
                                    <L7p:Type variableDataType="string"/>
                                </L7p:item>
                                <L7p:item binary="included">
                                    <L7p:CaseSensitive booleanValue="false"/>
                                    <L7p:RightValue stringValue="region"/>
                                </L7p:item>
                            </L7p:Predicates>
                        </L7p:ComparisonAssertion>
                        <L7p:EvaluateJsonPathExpression>
                            <L7p:Expression stringValue="$.Envelope.Body.ListarRegionOficinaResponse.O_COD"/>
                            <L7p:OtherTargetMessageVariable stringValue="responseJson"/>
                            <L7p:Target target="OTHER"/>
                            <L7p:VariablePrefix stringValue="countData"/>
                        </L7p:EvaluateJsonPathExpression>
                        <wsp:OneOrMore wsp:Usage="Required">
                            <wsp:All wsp:Usage="Required">
                                <L7p:ComparisonAssertion>
                                    <L7p:CaseSensitive booleanValue="false"/>
                                    <L7p:Expression1 stringValue="${countData.result}"/>
                                    <L7p:Expression2 stringValue="0"/>
                                    <L7p:Predicates predicates="included">
                                    <L7p:item binary="included">
                                    <L7p:CaseSensitive booleanValue="false"/>
                                    <L7p:RightValue stringValue="0"/>
                                    </L7p:item>
                                    </L7p:Predicates>
                                </L7p:ComparisonAssertion>
                                <L7p:EvaluateJsonPathExpression>
                                    <L7p:Expression stringValue="$.Envelope.Body.ListarRegionOficinaResponse.REGIONES"/>
                                    <L7p:OtherTargetMessageVariable stringValue="responseJson"/>
                                    <L7p:Target target="OTHER"/>
                                </L7p:EvaluateJsonPathExpression>
                                <L7p:SetVariable>
                                    <L7p:Base64Expression stringValue="JHtqc29uUGF0aC5yZXN1bHRzfQ=="/>
                                    <L7p:VariableToSet stringValue="comunasJson"/>
                                </L7p:SetVariable>
                                <L7p:Regex>
                                    <L7p:AutoTarget booleanValue="false"/>
                                    <L7p:OtherTargetMessageVariable stringValue="comunasJson"/>
                                    <L7p:Regex stringValue="CODI_REGION"/>
                                    <L7p:Replace booleanValue="true"/>
                                    <L7p:Replacement stringValue="codi_territorio"/>
                                    <L7p:Target target="OTHER"/>
                                </L7p:Regex>
                                <L7p:Regex>
                                    <L7p:AutoTarget booleanValue="false"/>
                                    <L7p:OtherTargetMessageVariable stringValue="comunasJson"/>
                                    <L7p:Regex stringValue="NOM_REGION"/>
                                    <L7p:Replace booleanValue="true"/>
                                    <L7p:Replacement stringValue="nom_territorio"/>
                                    <L7p:Target target="OTHER"/>
                                </L7p:Regex>
                                <L7p:SetVariable>
                                    <L7p:Base64Expression stringValue="ImNvZCI6IiR7Y291bnREYXRhLnJlc3VsdH0iLA0KInRlcnJpdG9yaW8iOlske2NvbXVuYXNKc29ufV0="/>
                                    <L7p:VariableToSet stringValue="body"/>
                                </L7p:SetVariable>
                                <L7p:SetVariable>
                                    <L7p:Base64Expression stringValue="MjAw"/>
                                    <L7p:VariableToSet stringValue="code"/>
                                </L7p:SetVariable>
                                <L7p:SetVariable>
                                    <L7p:Base64Expression stringValue="U3VjY2Vzc2Z1bCBvcGVyYXRpb24="/>
                                    <L7p:VariableToSet stringValue="description"/>
                                </L7p:SetVariable>
                                <L7p:SetVariable>
                                    <L7p:Base64Expression stringValue="U3VjY2Vzc2Z1bCBvcGVyYXRpb24="/>
                                    <L7p:VariableToSet stringValue="descriptionDetail"/>
                                </L7p:SetVariable>
                                <L7p:SetVariable>
                                    <L7p:Base64Expression stringValue="JHtyZXF1ZXN0LnRpbWUubG9jYWwueXl5eS9NTS9kZCdUJ0hIOm1tOnNzLlNTU30="/>
                                    <L7p:VariableToSet stringValue="responseTimestamp"/>
                                </L7p:SetVariable>
                                <L7p:Encapsulated>
                                    <L7p:EncapsulatedAssertionConfigGuid stringValue="2873d7c1-bfb2-42b8-ab9a-35767965de80"/>
                                    <L7p:EncapsulatedAssertionConfigName stringValue="API Portal Integration - Post Route"/>
                                    <L7p:Parameters mapValue="included">
                                    <L7p:entry>
                                    <L7p:key stringValue="portal.analytics.response.code"/>
                                    <L7p:value stringValue="200"/>
                                    </L7p:entry>
                                    <L7p:entry>
                                    <L7p:key stringValue="portal.analytics.routingTotalTime"/>
                                    <L7p:value stringValue="${request.elapsedTime}"/>
                                    </L7p:entry>
                                    </L7p:Parameters>
                                </L7p:Encapsulated>
                                <L7p:HardcodedResponse>
                                    <L7p:Base64ResponseBody stringValue="ewoicmVzdWx0Ijp7CgkidHJhbnNhY3Rpb25JZCI6IiR7cmVxdWVzdElkfSIsCgkiY29kZSI6IiR7Y29kZX0iLAoJImRlc2NyaXB0aW9uIjoiJHtkZXNjcmlwdGlvbn0iLAoJInJlc3BvbnNlVGltZXN0YW1wIjoiJHtyZXNwb25zZVRpbWVzdGFtcH0iCgl9LAoke2JvZHl9Cn0="/>
                                    <L7p:ResponseContentType stringValue="application/json; charset=UTF-8"/>
                                </L7p:HardcodedResponse>
                            </wsp:All>
                            <wsp:All wsp:Usage="Required">
                                <L7p:ComparisonAssertion>
                                    <L7p:CaseSensitive booleanValue="false"/>
                                    <L7p:Expression1 stringValue="${countData.result}"/>
                                    <L7p:Expression2 stringValue="1"/>
                                    <L7p:Predicates predicates="included">
                                    <L7p:item binary="included">
                                    <L7p:CaseSensitive booleanValue="false"/>
                                    <L7p:RightValue stringValue="1"/>
                                    </L7p:item>
                                    </L7p:Predicates>
                                </L7p:ComparisonAssertion>
                                <L7p:EvaluateJsonPathExpression>
                                    <L7p:Expression stringValue="$.Envelope.Body.ListarComunaRegionOficinaResponse.O_DESC"/>
                                    <L7p:OtherTargetMessageVariable stringValue="responseJson"/>
                                    <L7p:Target target="OTHER"/>
                                    <L7p:VariablePrefix stringValue="descriptionData"/>
                                </L7p:EvaluateJsonPathExpression>
                                <L7p:SetVariable>
                                    <L7p:Base64Expression stringValue="MjAw"/>
                                    <L7p:VariableToSet stringValue="code"/>
                                </L7p:SetVariable>
                                <L7p:SetVariable>
                                    <L7p:Base64Expression stringValue="U3VjY2Vzc2Z1bCBvcGVyYXRpb24="/>
                                    <L7p:VariableToSet stringValue="description"/>
                                </L7p:SetVariable>
                                <L7p:SetVariable>
                                    <L7p:Base64Expression stringValue="U3VjY2Vzc2Z1bCBvcGVyYXRpb24="/>
                                    <L7p:VariableToSet stringValue="descriptionDetail"/>
                                </L7p:SetVariable>
                                <L7p:SetVariable>
                                    <L7p:Base64Expression stringValue="JHtyZXF1ZXN0LnRpbWUubG9jYWwueXl5eS9NTS9kZCdUJ0hIOm1tOnNzLlNTU30="/>
                                    <L7p:VariableToSet stringValue="responseTimestamp"/>
                                </L7p:SetVariable>
                                <L7p:SetVariable>
                                    <L7p:Base64Expression stringValue="ImNvZCI6IiR7Y291bnREYXRhLnJlc3VsdH0iLA0KImRlc2NyaXB0aW9uIjoiJHtkZXNjcmlwdGlvbkRhdGEucmVzdWx0fSI="/>
                                    <L7p:VariableToSet stringValue="body"/>
                                </L7p:SetVariable>
                                <L7p:Encapsulated>
                                    <L7p:EncapsulatedAssertionConfigGuid stringValue="2873d7c1-bfb2-42b8-ab9a-35767965de80"/>
                                    <L7p:EncapsulatedAssertionConfigName stringValue="API Portal Integration - Post Route"/>
                                    <L7p:Parameters mapValue="included">
                                    <L7p:entry>
                                    <L7p:key stringValue="portal.analytics.response.code"/>
                                    <L7p:value stringValue="200"/>
                                    </L7p:entry>
                                    <L7p:entry>
                                    <L7p:key stringValue="portal.analytics.routingTotalTime"/>
                                    <L7p:value stringValue="${request.elapsedTime}"/>
                                    </L7p:entry>
                                    </L7p:Parameters>
                                </L7p:Encapsulated>
                                <L7p:HardcodedResponse>
                                    <L7p:Base64ResponseBody stringValue="ewoicmVzdWx0Ijp7CgkidHJhbnNhY3Rpb25JZCI6IiR7cmVxdWVzdElkfSIsCgkiY29kZSI6IiR7Y29kZX0iLAoJImRlc2NyaXB0aW9uIjoiJHtkZXNjcmlwdGlvbn0iLAoJInJlc3BvbnNlVGltZXN0YW1wIjoiJHtyZXNwb25zZVRpbWVzdGFtcH0iCgl9LAoke2JvZHl9Cn0="/>
                                    <L7p:ResponseContentType stringValue="application/json; charset=UTF-8"/>
                                </L7p:HardcodedResponse>
                            </wsp:All>
                        </wsp:OneOrMore>
                        <L7p:assertionComment>
                            <L7p:Properties mapValue="included">
                                <L7p:entry>
                                    <L7p:key stringValue="RIGHT.COMMENT"/>
                                    <L7p:value stringValue="generar respuesta para region"/>
                                </L7p:entry>
                            </L7p:Properties>
                        </L7p:assertionComment>
                    </wsp:All>
                </wsp:OneOrMore>
                <L7p:assertionComment>
                    <L7p:Properties mapValue="included">
                        <L7p:entry>
                            <L7p:key stringValue="RIGHT.COMMENT"/>
                            <L7p:value stringValue="http status 200"/>
                        </L7p:entry>
                    </L7p:Properties>
                </L7p:assertionComment>
            </wsp:All>
            <wsp:All wsp:Usage="Required">
                <L7p:SetVariable>
                    <L7p:Base64Expression stringValue="JHtodHRwUm91dGluZy5yZWFzb25Db2RlfQ=="/>
                    <L7p:VariableToSet stringValue="code"/>
                </L7p:SetVariable>
                <L7p:SetVariable>
                    <L7p:Base64Expression stringValue="QmFja2VuZCBlcnJvcg=="/>
                    <L7p:VariableToSet stringValue="description"/>
                </L7p:SetVariable>
                <L7p:SetVariable>
                    <L7p:Base64Expression stringValue="QmFja2VuZCBlcnJvcg=="/>
                    <L7p:VariableToSet stringValue="descriptionDetail"/>
                </L7p:SetVariable>
                <L7p:SetVariable>
                    <L7p:Base64Expression stringValue="JHtyZXF1ZXN0LnRpbWUubG9jYWwueXl5eS9NTS9kZCdUJ0hIOm1tOnNzLlNTU30="/>
                    <L7p:VariableToSet stringValue="responseTimestamp"/>
                </L7p:SetVariable>
                <L7p:Encapsulated>
                    <L7p:EncapsulatedAssertionConfigGuid stringValue="2873d7c1-bfb2-42b8-ab9a-35767965de80"/>
                    <L7p:EncapsulatedAssertionConfigName stringValue="API Portal Integration - Post Route"/>
                    <L7p:Parameters mapValue="included">
                        <L7p:entry>
                            <L7p:key stringValue="portal.analytics.response.code"/>
                            <L7p:value stringValue="200"/>
                        </L7p:entry>
                        <L7p:entry>
                            <L7p:key stringValue="portal.analytics.routingTotalTime"/>
                            <L7p:value stringValue="${request.elapsedTime}"/>
                        </L7p:entry>
                    </L7p:Parameters>
                </L7p:Encapsulated>
                <L7p:HardcodedResponse>
                    <L7p:Base64ResponseBody stringValue="ewoicmVzdWx0Ijp7CgkidHJhbnNhY3Rpb25JZCI6IiR7cmVxdWVzdElkfSIsCgkiY29kZSI6IiR7Y29kZX0iLAoJImRlc2NyaXB0aW9uIjoiJHtkZXNjcmlwdGlvbn0iLAoJInJlc3BvbnNlVGltZXN0YW1wIjoiJHtyZXNwb25zZVRpbWVzdGFtcH0iCgl9Cn0="/>
                    <L7p:ResponseContentType stringValue="application/json; charset=UTF-8"/>
                </L7p:HardcodedResponse>
                <L7p:assertionComment>
                    <L7p:Properties mapValue="included">
                        <L7p:entry>
                            <L7p:key stringValue="RIGHT.COMMENT"/>
                            <L7p:value stringValue="http status > 400"/>
                        </L7p:entry>
                    </L7p:Properties>
                </L7p:assertionComment>
            </wsp:All>
            <wsp:All wsp:Usage="Required">
                <L7p:ComparisonAssertion>
                    <L7p:CaseSensitive booleanValue="false"/>
                    <L7p:Expression1 stringValue="${httpRouting.reasonCode}"/>
                    <L7p:Operator operatorNull="null"/>
                    <L7p:Predicates predicates="included">
                        <L7p:item dataType="included">
                            <L7p:Type variableDataType="int"/>
                        </L7p:item>
                        <L7p:item binary="included">
                            <L7p:CaseSensitive booleanValue="false"/>
                            <L7p:RightValue stringValue="-1"/>
                        </L7p:item>
                    </L7p:Predicates>
                </L7p:ComparisonAssertion>
                <L7p:SetVariable>
                    <L7p:Base64Expression stringValue="MDUwMA=="/>
                    <L7p:VariableToSet stringValue="code"/>
                </L7p:SetVariable>
                <L7p:SetVariable>
                    <L7p:Base64Expression stringValue="SG9zdCBub3QgZm91bmQ="/>
                    <L7p:VariableToSet stringValue="description"/>
                </L7p:SetVariable>
                <L7p:SetVariable>
                    <L7p:Base64Expression stringValue="SW50ZXJuYWwgZXJyb3I="/>
                    <L7p:VariableToSet stringValue="descriptionDetail"/>
                </L7p:SetVariable>
                <L7p:SetVariable>
                    <L7p:Base64Expression stringValue="JHtyZXF1ZXN0LnRpbWUubG9jYWwueXl5eS9NTS9kZCdUJ0hIOm1tOnNzLlNTU30="/>
                    <L7p:VariableToSet stringValue="responseTimestamp"/>
                </L7p:SetVariable>
                <L7p:CustomizeErrorResponse>
                    <L7p:Content stringValueReference="inline"><![CDATA[{
"result":{
	"transactionId":"${requestId}",
	"code":"${code}",
	"description":"${description}",
	"descriptionDetail":"${descriptionDetail}",
	"responseTimestamp":"${responseTimestamp}"
	}
}]]></L7p:Content>
                    <L7p:ContentType stringValue="application/json; charset=UTF-8"/>
                    <L7p:ExtraHeaders nameValuePairArray="included"/>
                </L7p:CustomizeErrorResponse>
                <L7p:Encapsulated>
                    <L7p:EncapsulatedAssertionConfigGuid stringValue="2873d7c1-bfb2-42b8-ab9a-35767965de80"/>
                    <L7p:EncapsulatedAssertionConfigName stringValue="API Portal Integration - Post Route"/>
                    <L7p:Parameters mapValue="included">
                        <L7p:entry>
                            <L7p:key stringValue="portal.analytics.response.code"/>
                            <L7p:value stringValue="500"/>
                        </L7p:entry>
                        <L7p:entry>
                            <L7p:key stringValue="portal.analytics.routingTotalTime"/>
                            <L7p:value stringValue="${request.elapsedTime}"/>
                        </L7p:entry>
                    </L7p:Parameters>
                </L7p:Encapsulated>
                <L7p:RaiseError/>
                <L7p:assertionComment>
                    <L7p:Properties mapValue="included">
                        <L7p:entry>
                            <L7p:key stringValue="RIGHT.COMMENT"/>
                            <L7p:value stringValue="http status -1"/>
                        </L7p:entry>
                    </L7p:Properties>
                </L7p:assertionComment>
            </wsp:All>
            <wsp:All wsp:Usage="Required">
                <L7p:ComparisonAssertion>
                    <L7p:CaseSensitive booleanValue="false"/>
                    <L7p:Expression1 stringValue="${httpRouting.reasonCode}"/>
                    <L7p:Operator operatorNull="null"/>
                    <L7p:Predicates predicates="included">
                        <L7p:item dataType="included">
                            <L7p:Type variableDataType="int"/>
                        </L7p:item>
                        <L7p:item binary="included">
                            <L7p:CaseSensitive booleanValue="false"/>
                            <L7p:RightValue stringValue="-2"/>
                        </L7p:item>
                    </L7p:Predicates>
                </L7p:ComparisonAssertion>
                <L7p:SetVariable>
                    <L7p:Base64Expression stringValue="MDUwMA=="/>
                    <L7p:VariableToSet stringValue="code"/>
                </L7p:SetVariable>
                <L7p:SetVariable>
                    <L7p:Base64Expression stringValue="QmFkIHVybA=="/>
                    <L7p:VariableToSet stringValue="description"/>
                </L7p:SetVariable>
                <L7p:SetVariable>
                    <L7p:Base64Expression stringValue="SW50ZXJuYWwgZXJyb3I="/>
                    <L7p:VariableToSet stringValue="descriptionDetail"/>
                </L7p:SetVariable>
                <L7p:SetVariable>
                    <L7p:Base64Expression stringValue="JHtyZXF1ZXN0LnRpbWUubG9jYWwueXl5eS9NTS9kZCdUJ0hIOm1tOnNzLlNTU30="/>
                    <L7p:VariableToSet stringValue="responseTimestamp"/>
                </L7p:SetVariable>
                <L7p:CustomizeErrorResponse>
                    <L7p:Content stringValueReference="inline"><![CDATA[{
"result":{
	"transactionId":"${requestId}",
	"code":"${code}",
	"description":"${description}",
	"descriptionDetail":"${descriptionDetail}",
	"responseTimestamp":"${responseTimestamp}"
	}
}]]></L7p:Content>
                    <L7p:ContentType stringValue="application/json; charset=UTF-8"/>
                    <L7p:ExtraHeaders nameValuePairArray="included"/>
                </L7p:CustomizeErrorResponse>
                <L7p:Encapsulated>
                    <L7p:EncapsulatedAssertionConfigGuid stringValue="2873d7c1-bfb2-42b8-ab9a-35767965de80"/>
                    <L7p:EncapsulatedAssertionConfigName stringValue="API Portal Integration - Post Route"/>
                    <L7p:Parameters mapValue="included">
                        <L7p:entry>
                            <L7p:key stringValue="portal.analytics.response.code"/>
                            <L7p:value stringValue="500"/>
                        </L7p:entry>
                        <L7p:entry>
                            <L7p:key stringValue="portal.analytics.routingTotalTime"/>
                            <L7p:value stringValue="${request.elapsedTime}"/>
                        </L7p:entry>
                    </L7p:Parameters>
                </L7p:Encapsulated>
                <L7p:RaiseError/>
                <L7p:assertionComment>
                    <L7p:Properties mapValue="included">
                        <L7p:entry>
                            <L7p:key stringValue="RIGHT.COMMENT"/>
                            <L7p:value stringValue="http status -2"/>
                        </L7p:entry>
                    </L7p:Properties>
                </L7p:assertionComment>
            </wsp:All>
            <wsp:All wsp:Usage="Required">
                <L7p:ComparisonAssertion>
                    <L7p:CaseSensitive booleanValue="false"/>
                    <L7p:Expression1 stringValue="${httpRouting.reasonCode}"/>
                    <L7p:Operator operatorNull="null"/>
                    <L7p:Predicates predicates="included">
                        <L7p:item dataType="included">
                            <L7p:Type variableDataType="int"/>
                        </L7p:item>
                        <L7p:item binary="included">
                            <L7p:CaseSensitive booleanValue="false"/>
                            <L7p:RightValue stringValue="-3"/>
                        </L7p:item>
                    </L7p:Predicates>
                </L7p:ComparisonAssertion>
                <L7p:SetVariable>
                    <L7p:Base64Expression stringValue="MDUwMA=="/>
                    <L7p:VariableToSet stringValue="code"/>
                </L7p:SetVariable>
                <L7p:SetVariable>
                    <L7p:Base64Expression stringValue="Q29uZXhpb24gdGltZW91dA=="/>
                    <L7p:VariableToSet stringValue="description"/>
                </L7p:SetVariable>
                <L7p:SetVariable>
                    <L7p:Base64Expression stringValue="SW50ZXJuYWwgZXJyb3I="/>
                    <L7p:VariableToSet stringValue="descriptionDetail"/>
                </L7p:SetVariable>
                <L7p:SetVariable>
                    <L7p:Base64Expression stringValue="JHtyZXF1ZXN0LnRpbWUubG9jYWwueXl5eS9NTS9kZCdUJ0hIOm1tOnNzLlNTU30="/>
                    <L7p:VariableToSet stringValue="responseTimestamp"/>
                </L7p:SetVariable>
                <L7p:CustomizeErrorResponse>
                    <L7p:Content stringValueReference="inline"><![CDATA[{
"result":{
	"transactionId":"${requestId}",
	"code":"${code}",
	"description":"${description}",
	"descriptionDetail":"${descriptionDetail}",
	"responseTimestamp":"${responseTimestamp}"
	}
}]]></L7p:Content>
                    <L7p:ContentType stringValue="application/json; charset=UTF-8"/>
                    <L7p:ExtraHeaders nameValuePairArray="included"/>
                </L7p:CustomizeErrorResponse>
                <L7p:Encapsulated>
                    <L7p:EncapsulatedAssertionConfigGuid stringValue="2873d7c1-bfb2-42b8-ab9a-35767965de80"/>
                    <L7p:EncapsulatedAssertionConfigName stringValue="API Portal Integration - Post Route"/>
                    <L7p:Parameters mapValue="included">
                        <L7p:entry>
                            <L7p:key stringValue="portal.analytics.response.code"/>
                            <L7p:value stringValue="500"/>
                        </L7p:entry>
                        <L7p:entry>
                            <L7p:key stringValue="portal.analytics.routingTotalTime"/>
                            <L7p:value stringValue="${request.elapsedTime}"/>
                        </L7p:entry>
                    </L7p:Parameters>
                </L7p:Encapsulated>
                <L7p:RaiseError/>
                <L7p:assertionComment>
                    <L7p:Properties mapValue="included">
                        <L7p:entry>
                            <L7p:key stringValue="RIGHT.COMMENT"/>
                            <L7p:value stringValue="http status -3"/>
                        </L7p:entry>
                    </L7p:Properties>
                </L7p:assertionComment>
            </wsp:All>
            <wsp:All wsp:Usage="Required">
                <L7p:ComparisonAssertion>
                    <L7p:CaseSensitive booleanValue="false"/>
                    <L7p:Expression1 stringValue="${httpRouting.reasonCode}"/>
                    <L7p:Operator operatorNull="null"/>
                    <L7p:Predicates predicates="included">
                        <L7p:item dataType="included">
                            <L7p:Type variableDataType="int"/>
                        </L7p:item>
                        <L7p:item binary="included">
                            <L7p:CaseSensitive booleanValue="false"/>
                            <L7p:RightValue stringValue="-4"/>
                        </L7p:item>
                    </L7p:Predicates>
                </L7p:ComparisonAssertion>
                <L7p:SetVariable>
                    <L7p:Base64Expression stringValue="MDUwMA=="/>
                    <L7p:VariableToSet stringValue="code"/>
                </L7p:SetVariable>
                <L7p:SetVariable>
                    <L7p:Base64Expression stringValue="UmVhZCB0aW1lb3V0"/>
                    <L7p:VariableToSet stringValue="description"/>
                </L7p:SetVariable>
                <L7p:SetVariable>
                    <L7p:Base64Expression stringValue="SW50ZXJuYWwgZXJyb3I="/>
                    <L7p:VariableToSet stringValue="descriptionDetail"/>
                </L7p:SetVariable>
                <L7p:SetVariable>
                    <L7p:Base64Expression stringValue="JHtyZXF1ZXN0LnRpbWUubG9jYWwueXl5eS9NTS9kZCdUJ0hIOm1tOnNzLlNTU30="/>
                    <L7p:VariableToSet stringValue="responseTimestamp"/>
                </L7p:SetVariable>
                <L7p:CustomizeErrorResponse>
                    <L7p:Content stringValueReference="inline"><![CDATA[{
"result":{
	"transactionId":"${requestId}",
	"code":"${code}",
	"description":"${description}",
	"descriptionDetail":"${descriptionDetail}",
	"responseTimestamp":"${responseTimestamp}"
	}
}]]></L7p:Content>
                    <L7p:ContentType stringValue="application/json; charset=UTF-8"/>
                    <L7p:ExtraHeaders nameValuePairArray="included"/>
                </L7p:CustomizeErrorResponse>
                <L7p:Encapsulated>
                    <L7p:EncapsulatedAssertionConfigGuid stringValue="2873d7c1-bfb2-42b8-ab9a-35767965de80"/>
                    <L7p:EncapsulatedAssertionConfigName stringValue="API Portal Integration - Post Route"/>
                    <L7p:Parameters mapValue="included">
                        <L7p:entry>
                            <L7p:key stringValue="portal.analytics.response.code"/>
                            <L7p:value stringValue="500"/>
                        </L7p:entry>
                        <L7p:entry>
                            <L7p:key stringValue="portal.analytics.routingTotalTime"/>
                            <L7p:value stringValue="${request.elapsedTime}"/>
                        </L7p:entry>
                    </L7p:Parameters>
                </L7p:Encapsulated>
                <L7p:RaiseError/>
                <L7p:assertionComment>
                    <L7p:Properties mapValue="included">
                        <L7p:entry>
                            <L7p:key stringValue="RIGHT.COMMENT"/>
                            <L7p:value stringValue="http status -4"/>
                        </L7p:entry>
                    </L7p:Properties>
                </L7p:assertionComment>
            </wsp:All>
            <wsp:All wsp:Usage="Required">
                <L7p:ComparisonAssertion>
                    <L7p:CaseSensitive booleanValue="false"/>
                    <L7p:Expression1 stringValue="${httpRouting.reasonCode}"/>
                    <L7p:Operator operatorNull="null"/>
                    <L7p:Predicates predicates="included">
                        <L7p:item dataType="included">
                            <L7p:Type variableDataType="int"/>
                        </L7p:item>
                        <L7p:item binary="included">
                            <L7p:CaseSensitive booleanValue="false"/>
                            <L7p:RightValue stringValue="-5"/>
                        </L7p:item>
                    </L7p:Predicates>
                </L7p:ComparisonAssertion>
                <L7p:SetVariable>
                    <L7p:Base64Expression stringValue="MDUwMA=="/>
                    <L7p:VariableToSet stringValue="code"/>
                </L7p:SetVariable>
                <L7p:SetVariable>
                    <L7p:Base64Expression stringValue="VW5kZWZpbmVk"/>
                    <L7p:VariableToSet stringValue="description"/>
                </L7p:SetVariable>
                <L7p:SetVariable>
                    <L7p:Base64Expression stringValue="SW50ZXJuYWwgZXJyb3I="/>
                    <L7p:VariableToSet stringValue="descriptionDetail"/>
                </L7p:SetVariable>
                <L7p:SetVariable>
                    <L7p:Base64Expression stringValue="JHtyZXF1ZXN0LnRpbWUubG9jYWwueXl5eS9NTS9kZCdUJ0hIOm1tOnNzLlNTU30="/>
                    <L7p:VariableToSet stringValue="responseTimestamp"/>
                </L7p:SetVariable>
                <L7p:CustomizeErrorResponse>
                    <L7p:Content stringValueReference="inline"><![CDATA[{
"result":{
	"transactionId":"${requestId}",
	"code":"${code}",
	"description":"${description}",
	"descriptionDetail":"${descriptionDetail}",
	"responseTimestamp":"${responseTimestamp}"
	}
}]]></L7p:Content>
                    <L7p:ContentType stringValue="application/json; charset=UTF-8"/>
                    <L7p:ExtraHeaders nameValuePairArray="included"/>
                </L7p:CustomizeErrorResponse>
                <L7p:Encapsulated>
                    <L7p:EncapsulatedAssertionConfigGuid stringValue="2873d7c1-bfb2-42b8-ab9a-35767965de80"/>
                    <L7p:EncapsulatedAssertionConfigName stringValue="API Portal Integration - Post Route"/>
                    <L7p:Parameters mapValue="included">
                        <L7p:entry>
                            <L7p:key stringValue="portal.analytics.response.code"/>
                            <L7p:value stringValue="500"/>
                        </L7p:entry>
                        <L7p:entry>
                            <L7p:key stringValue="portal.analytics.routingTotalTime"/>
                            <L7p:value stringValue="${request.elapsedTime}"/>
                        </L7p:entry>
                    </L7p:Parameters>
                </L7p:Encapsulated>
                <L7p:RaiseError/>
                <L7p:assertionComment>
                    <L7p:Properties mapValue="included">
                        <L7p:entry>
                            <L7p:key stringValue="RIGHT.COMMENT"/>
                            <L7p:value stringValue="http status -5"/>
                        </L7p:entry>
                    </L7p:Properties>
                </L7p:assertionComment>
            </wsp:All>
        </wsp:OneOrMore>
    </wsp:All>
</wsp:Policy>